terrascan/__init__.py
terrascan/terrascan.py
terrascan/embedded/__init__.py
terrascan/embedded/terraform_validate/__init__.py
terrascan/embedded/terraform_validate/terraform_validate.py
tests/__init__.py
tests/test_terrascan.py
tests/infrastructure/fail/gcp_main.tf
tests/infrastructure/fail/main.tf
tests/infrastructure/fail/s3_related.tf
tests/infrastructure/success/main.tf
Terrascan-0.2.3.dist-info/AUTHORS.rst
Terrascan-0.2.3.dist-info/LICENSE
Terrascan-0.2.3.dist-info/METADATA
Terrascan-0.2.3.dist-info/WHEEL
Terrascan-0.2.3.dist-info/entry_points.txt
Terrascan-0.2.3.dist-info/top_level.txt
Terrascan-0.2.3.dist-info/RECORD
