Metadata-Version: 2.1
Name: Terrascan
Version: 0.2.3
Summary: Security best practice static code analysis for terraform
Home-page: https://github.com/accurics/terrascan
Author: Accurics
Author-email: support@accurics.com
License: Apache-2.0
Download-URL: https://github.com/accurics/terrascan/archive/v0.2.3.tar.gz
Keywords: terrascan
Platform: UNKNOWN
Classifier: Development Status :: 5 - Production/Stable
Classifier: Intended Audience :: Developers
Classifier: License :: OSI Approved :: Apache Software License
Classifier: Natural Language :: English
Classifier: Programming Language :: Python :: 3.6
Classifier: Programming Language :: Python :: 3.7
Classifier: Programming Language :: Python :: 3.8
Requires-Dist: pyhcl (>=0.4.4)
